{
  "links": [
    {
      "discriminant": "link",
      "value": {
        "label": "Startseite",
        "href": "/"
      }
    },
    {
      "discriminant": "page",
      "value": {
        "label": "Konferenzen",
        "id": "conferences"
      }
    },
    {
      "discriminant": "page",
      "value": {
        "label": "Publikationen",
        "id": "publications"
      }
    },
    {
      "discriminant": "page",
      "value": {
        "label": "Steering committee",
        "id": "steering-committee"
      }
    },
    {
      "discriminant": "link",
      "value": {
        "label": "Links",
        "href": "links"
      }
    }
  ]
}
